{
"1": "_*CEK NOLEP*_\n\nNama: {nama}\nTingkat Nolep: 1%\n\nStatus:\nHampir normal. Masih ada kehidupan.",
"2": "_*CEK NOLEP*_\n\nNama: {nama}\nTingkat Nolep: 2%\n\nStatus:\nMasih keluar rumah sesekali.",
"3": "_*CEK NOLEP*_\n\nNama: {nama}\nTingkat Nolep: 3%\n\nStatus:\nSedikit nolep. Tapi masih napas.",
"4": "_*CEK NOLEP*_\n\nNama: {nama}\nTingkat Nolep: 4%\n\nStatus:\nMasih ada teman, walau jarang.",
"5": "_*CEK NOLEP*_\n\nNama: {nama}\nTingkat Nolep: 5%\n\nStatus:\nNolep pemula. Belum parah.",
"6": "_*CEK NOLEP*_\n\nNama: {nama}\nTingkat Nolep: 6%\n\nStatus:\nKadang keluar. Masih aman.",
"7": "_*CEK NOLEP*_\n\nNama: {nama}\nTingkat Nolep: 7%\n\nStatus:\nMulai jarang nongkrong.",
"8": "_*CEK NOLEP*_\n\nNama: {nama}\nTingkat Nolep: 8%\n\nStatus:\nSedikit betah di rumah.",
"9": "_*CEK NOLEP*_\n\nNama: {nama}\nTingkat Nolep: 9%\n\nStatus:\nHampir 10%. Masih terkendali.",
"10": "_*CEK NOLEP*_\n\nNama: {nama}\nTingkat Nolep: 10%\n\nStatus:\nNolep ringan. Tapi mulai waspada.",
"11": "_*CEK NOLEP*_\n\nNama: {nama}\nTingkat Nolep: 11%\n\nStatus:\nMulai sering di kamar.",
"12": "_*CEK NOLEP*_\n\nNama: {nama}\nTingkat Nolep: 12%\n\nStatus:\nLumayan nolep.",
"13": "_*CEK NOLEP*_\n\nNama: {nama}\nTingkat Nolep: 13%\n\nStatus:\nJarang keluar.",
"14": "_*CEK NOLEP*_\n\nNama: {nama}\nTingkat Nolep: 14%\n\nStatus:\nMasih mending.",
"15": "_*CEK NOLEP*_\n\nNama: {nama}\nTingkat Nolep: 15%\n\nStatus:\nLumayan betah sendirian.",
"16": "_*CEK NOLEP*_\n\nNama: {nama}\nTingkat Nolep: 16%\n\nStatus:\nMulai parah.",
"17": "_*CEK NOLEP*_\n\nNama: {nama}\nTingkat Nolep: 17%\n\nStatus:\nSering di rumah.",
"18": "_*CEK NOLEP*_\n\nNama: {nama}\nTingkat Nolep: 18%\n\nStatus:\nLumayan jarang nongkrong.",
"19": "_*CEK NOLEP*_\n\nNama: {nama}\nTingkat Nolep: 19%\n\nStatus:\nHampir 20%.",
"20": "_*CEK NOLEP*_\n\nNama: {nama}\nTingkat Nolep: 20%\n\nStatus:\nNolep pemula tapi mulai terasa.",
"21": "_*CEK NOLEP*_\n\nNama: {nama}\nTingkat Nolep: 21%\n\nStatus:\nMulai jarang keluar.",
"22": "_*CEK NOLEP*_\n\nNama: {nama}\nTingkat Nolep: 22%\n\nStatus:\nLumayan nolep.",
"23": "_*CEK NOLEP*_\n\nNama: {nama}\nTingkat Nolep: 23%\n\nStatus:\nSering di kamar.",
"24": "_*CEK NOLEP*_\n\nNama: {nama}\nTingkat Nolep: 24%\n\nStatus:\nMulai malas keluar.",
"25": "_*CEK NOLEP*_\n\nNama: {nama}\nTingkat Nolep: 25%\n\nStatus:\nSeperempat nolep.",
"26": "_*CEK NOLEP*_\n\nNama: {nama}\nTingkat Nolep: 26%\n\nStatus:\nLumayan betah sendiri.",
"27": "_*CEK NOLEP*_\n\nNama: {nama}\nTingkat Nolep: 27%\n\nStatus:\nMulai jarang interaksi.",
"28": "_*CEK NOLEP*_\n\nNama: {nama}\nTingkat Nolep: 28%\n\nStatus:\nLumayan nolep.",
"29": "_*CEK NOLEP*_\n\nNama: {nama}\nTingkat Nolep: 29%\n\nStatus:\nHampir 30%.",
"30": "_*CEK NOLEP*_\n\nNama: {nama}\nTingkat Nolep: 30%\n\nStatus:\nNolep level menengah.",
"31": "_*CEK NOLEP*_\n\nNama: {nama}\nTingkat Nolep: 31%\n\nStatus:\nSering di kamar.",
"32": "_*CEK NOLEP*_\n\nNama: {nama}\nTingkat Nolep: 32%\n\nStatus:\nLumayan jarang keluar.",
"33": "_*CEK NOLEP*_\n\nNama: {nama}\nTingkat Nolep: 33%\n\nStatus:\nMulai parah.",
"34": "_*CEK NOLEP*_\n\nNama: {nama}\nTingkat Nolep: 34%\n\nStatus:\nBetah sendiri.",
"35": "_*CEK NOLEP*_\n\nNama: {nama}\nTingkat Nolep: 35%\n\nStatus:\nLumayan nolep.",
"36": "_*CEK NOLEP*_\n\nNama: {nama}\nTingkat Nolep: 36%\n\nStatus:\nSering sendirian.",
"37": "_*CEK NOLEP*_\n\nNama: {nama}\nTingkat Nolep: 37%\n\nStatus:\nLumayan kronis.",
"38": "_*CEK NOLEP*_\n\nNama: {nama}\nTingkat Nolep: 38%\n\nStatus:\nJarang bersosialisasi.",
"39": "_*CEK NOLEP*_\n\nNama: {nama}\nTingkat Nolep: 39%\n\nStatus:\nHampir 40%.",
"40": "_*CEK NOLEP*_\n\nNama: {nama}\nTingkat Nolep: 40%\n\nStatus:\nNolep level menengah.",
"41": "_*CEK NOLEP*_\n\nNama: {nama}\nTingkat Nolep: 41%\n\nStatus:\nLumayan kesepian.",
"42": "_*CEK NOLEP*_\n\nNama: {nama}\nTingkat Nolep: 42%\n\nStatus:\nSering di rumah.",
"43": "_*CEK NOLEP*_\n\nNama: {nama}\nTingkat Nolep: 43%\n\nStatus:\nLumayan parah.",
"44": "_*CEK NOLEP*_\n\nNama: {nama}\nTingkat Nolep: 44%\n\nStatus:\nHampir setengah.",
"45": "_*CEK NOLEP*_\n\nNama: {nama}\nTingkat Nolep: 45%\n\nStatus:\nBetah sendiri.",
"46": "_*CEK NOLEP*_\n\nNama: {nama}\nTingkat Nolep: 46%\n\nStatus:\nLumayan nolep.",
"47": "_*CEK NOLEP*_\n\nNama: {nama}\nTingkat Nolep: 47%\n\nStatus:\nSering di kamar.",
"48": "_*CEK NOLEP*_\n\nNama: {nama}\nTingkat Nolep: 48%\n\nStatus:\nHampir 50%.",
"49": "_*CEK NOLEP*_\n\nNama: {nama}\nTingkat Nolep: 49%\n\nStatus:\nNyaris setengah.",
"50": "_*CEK NOLEP*_\n\nNama: {nama}\nTingkat Nolep: 50%\n\nStatus:\nSetengah nolep.",
"51": "_*CEK NOLEP*_\n\nNama: {nama}\nTingkat Nolep: 51%\n\nStatus:\nUdah lewat setengah.",
"52": "_*CEK NOLEP*_\n\nNama: {nama}\nTingkat Nolep: 52%\n\nStatus:\nLumayan kronis.",
"53": "_*CEK NOLEP*_\n\nNama: {nama}\nTingkat Nolep: 53%\n\nStatus:\nSering di rumah.",
"54": "_*CEK NOLEP*_\n\nNama: {nama}\nTingkat Nolep: 54%\n\nStatus:\nLumayan parah.",
"55": "_*CEK NOLEP*_\n\nNama: {nama}\nTingkat Nolep: 55%\n\nStatus:\nNolep serius.",
"56": "_*CEK NOLEP*_\n\nNama: {nama}\nTingkat Nolep: 56%\n\nStatus:\nJarang keluar.",
"57": "_*CEK NOLEP*_\n\nNama: {nama}\nTingkat Nolep: 57%\n\nStatus:\nLumayan kronis.",
"58": "_*CEK NOLEP*_\n\nNama: {nama}\nTingkat Nolep: 58%\n\nStatus:\nSering sendirian.",
"59": "_*CEK NOLEP*_\n\nNama: {nama}\nTingkat Nolep: 59%\n\nStatus:\nHampir 60%.",
"60": "_*CEK NOLEP*_\n\nNama: {nama}\nTingkat Nolep: 60%\n\nStatus:\nNolep veteran.",
"61": "_*CEK NOLEP*_\n\nNama: {nama}\nTingkat Nolep: 61%\n\nStatus:\nSering di kamar.",
"62": "_*CEK NOLEP*_\n\nNama: {nama}\nTingkat Nolep: 62%\n\nStatus:\nJarang sosialisasi.",
"63": "_*CEK NOLEP*_\n\nNama: {nama}\nTingkat Nolep: 63%\n\nStatus:\nLumayan parah.",
"64": "_*CEK NOLEP*_\n\nNama: {nama}\nTingkat Nolep: 64%\n\nStatus:\nNolep berat.",
"65": "_*CEK NOLEP*_\n\nNama: {nama}\nTingkat Nolep: 65%\n\nStatus:\nMulai ekstrem.",
"66": "_*CEK NOLEP*_\n\nNama: {nama}\nTingkat Nolep: 66%\n\nStatus:\nSering sendiri.",
"67": "_*CEK NOLEP*_\n\nNama: {nama}\nTingkat Nolep: 67%\n\nStatus:\nLumayan kronis.",
"68": "_*CEK NOLEP*_\n\nNama: {nama}\nTingkat Nolep: 68%\n\nStatus:\nNolep senior.",
"69": "_*CEK NOLEP*_\n\nNama: {nama}\nTingkat Nolep: 69%\n\nStatus:\nHampir 70%.",
"70": "_*CEK NOLEP*_\n\nNama: {nama}\nTingkat Nolep: 70%\n\nStatus:\nNolep berat.",
"71": "_*CEK NOLEP*_\n\nNama: {nama}\nTingkat Nolep: 71%\n\nStatus:\nUdah jarang keluar.",
"72": "_*CEK NOLEP*_\n\nNama: {nama}\nTingkat Nolep: 72%\n\nStatus:\nKronis.",
"73": "_*CEK NOLEP*_\n\nNama: {nama}\nTingkat Nolep: 73%\n\nStatus:\nLumayan parah.",
"74": "_*CEK NOLEP*_\n\nNama: {nama}\nTingkat Nolep: 74%\n\nStatus:\nNolep hardcore.",
"75": "_*CEK NOLEP*_\n\nNama: {nama}\nTingkat Nolep: 75%\n\nStatus:\nEkstrem.",
"76": "_*CEK NOLEP*_\n\nNama: {nama}\nTingkat Nolep: 76%\n\nStatus:\nParah banget.",
"77": "_*CEK NOLEP*_\n\nNama: {nama}\nTingkat Nolep: 77%\n\nStatus:\nLegenda nolep.",
"78": "_*CEK NOLEP*_\n\nNama: {nama}\nTingkat Nolep: 78%\n\nStatus:\nKronis.",
"79": "_*CEK NOLEP*_\n\nNama: {nama}\nTingkat Nolep: 79%\n\nStatus:\nHampir 80%.",
"80": "_*CEK NOLEP*_\n\nNama: {nama}\nTingkat Nolep: 80%\n\nStatus:\nTingkat dewa nolep.",
"81": "_*CEK NOLEP*_\n\nNama: {nama}\nTingkat Nolep: 81%\n\nStatus:\nUdah terlalu nolep.",
"82": "_*CEK NOLEP*_\n\nNama: {nama}\nTingkat Nolep: 82%\n\nStatus:\nLegenda kamar.",
"83": "_*CEK NOLEP*_\n\nNama: {nama}\nTingkat Nolep: 83%\n\nStatus:\nParah.",
"84": "_*CEK NOLEP*_\n\nNama: {nama}\nTingkat Nolep: 84%\n\nStatus:\nNolep sejati.",
"85": "_*CEK NOLEP*_\n\nNama: {nama}\nTingkat Nolep: 85%\n\nStatus:\nUdah susah keluar.",
"86": "_*CEK NOLEP*_\n\nNama: {nama}\nTingkat Nolep: 86%\n\nStatus:\nKronis.",
"87": "_*CEK NOLEP*_\n\nNama: {nama}\nTingkat Nolep: 87%\n\nStatus:\nLegenda nolep.",
"88": "_*CEK NOLEP*_\n\nNama: {nama}\nTingkat Nolep: 88%\n\nStatus:\nAbadi.",
"89": "_*CEK NOLEP*_\n\nNama: {nama}\nTingkat Nolep: 89%\n\nStatus:\nHampir maksimal.",
"90": "_*CEK NOLEP*_\n\nNama: {nama}\nTingkat Nolep: 90%\n\nStatus:\nMaster nolep.",
"91": "_*CEK NOLEP*_\n\nNama: {nama}\nTingkat Nolep: 91%\n\nStatus:\nDewa kamar.",
"92": "_*CEK NOLEP*_\n\nNama: {nama}\nTingkat Nolep: 92%\n\nStatus:\nLegenda.",
"93": "_*CEK NOLEP*_\n\nNama: {nama}\nTingkat Nolep: 93%\n\nStatus:\nParah banget.",
"94": "_*CEK NOLEP*_\n\nNama: {nama}\nTingkat Nolep: 94%\n\nStatus:\nHampir sempurna nolep.",
"95": "_*CEK NOLEP*_\n\nNama: {nama}\nTingkat Nolep: 95%\n\nStatus:\nNolep sejati.",
"96": "_*CEK NOLEP*_\n\nNama: {nama}\nTingkat Nolep: 96%\n\nStatus:\nKamar adalah dunia.",
"97": "_*CEK NOLEP*_\n\nNama: {nama}\nTingkat Nolep: 97%\n\nStatus:\nLegenda nolep.",
"98": "_*CEK NOLEP*_\n\nNama: {nama}\nTingkat Nolep: 98%\n\nStatus:\nHampir maksimal.",
"99": "_*CEK NOLEP*_\n\nNama: {nama}\nTingkat Nolep: 99%\n\nStatus:\nNyaris nolep sempurna.",
"100": "_*CEK NOLEP*_\n\nNama: {nama}\nTingkat Nolep: 100%\n\nStatus:\nNOLEP ABSOLUT. Dunia luar cuma mitos."
}